setup.py
jdistributions/Binomialdistribution.py
jdistributions/Gaussiandistribution.py
jdistributions/Generaldistribution.py
jdistributions/__init__.py
jdistributions.egg-info/PKG-INFO
jdistributions.egg-info/SOURCES.txt
jdistributions.egg-info/dependency_links.txt
jdistributions.egg-info/not-zip-safe
jdistributions.egg-info/top_level.txt