Metadata-Version: 1.0
Name: jdistributions
Version: 0.1
Summary: Data Distribution - Gaussian and Binomial
Home-page: UNKNOWN
Author: Jish N
Author-email: UNKNOWN
License: UNKNOWN
Platform: UNKNOWN
